{
  "week_number": 11,
  "subject": "SOCDS 2025/26 Update Week #11 - PreK Orange",
  "date": "2025-11-15",
  "text": "Email Ms. Annemarie\nPaperpie\nVirtual BookFair\nWe are excited to partner with\nPaperPie\n(formerly\nUsborne Books\n) to host a\nVirtual Book Fair\n! These beautifully made, age-appropriate books make wonderful gifts for children and families.\nThrough this partnership, our school earns free books that we donate to local programs in need of new reading materials. In previous years, we’ve partnered with\nUTCAO Preschool\n(across from Home Depot) to help them expand their classroom library—and we’re proud to continue that tradition of sharing the joy of reading with others.\nThe link to their\nonline catelog is here\n.\nFriends of SO Public Library\nJewelry Sale\nSaturday November 15, from 10am to 5pm\nSunday November 16, from 1pm to 4pm\nBaird Community Center, 5 Mead Street, South Orange\nThe Friends of the South Orange Public Library are a dedicated group of volunteers who fundraise to enhance library programs and services for our community. They are hosting a jewelry sale at the Baird Center, and it’s a wonderful opportunity to support the library while getting a head start on your holiday shopping.\nGardening with Ms. Linda\nOver the past two weeks we have planted over 125 bulbs. Except for the tulips, all the bulbs have been selected because they are deer deterrent. The snowdrops (Galanthus) will bloom first, as early as February, followed by tulips, daffodils, winter windflower (Anemone blanda) and summer \r\nsnowflakes (Leucojum aestivum) by mid-spring. Rising 32 inches in height and adored by bees, butterflies and other pollinators, Allium purple sensation is the last of our bulbs to bloom in late spring or early summer. It has been challenging to dig and plant bulbs as the temperatures drop but we stay warm by keeping busy. We’ve been raking leaves and adding them to the compost bin to achieve a balance between “brown” and “green” materials.  It was exciting to chop up a pumpkin and examine the fungi that was growing on the inside before feeding it to the “decomposers” in the bin.\nPEP Thanksgiving Placements\nOLS Thanksgiving Food Distribution\nThank you to our wonderful SOCDS PEP team for organizing a meaningful opportunity for our students to spread caring throughout our community. Mary Payne (Ruby’s mom) created the beautiful placement design above, and Rachel Pattison (Luca’s mom) has coordinated the distribution to the OLS Thanksgiving Food Drive. Next week, the children will color their placements in class, and we will laminate them before they are shared.\nDoing for others is a powerful way for children to understand empathy, generosity, and the impact of small acts of kindness.\nChildren will not sign their placements, and there will be no identification of where they came from in \r\norder to protect our students.\nIf you have any questions or concerns please text (1-646-226-8790) or email learn@socds.com.\nAnnemarie\nArt with Ms. Jenny\nMs. Jenny used a variety of techniques to create dream catchers and totem poles.\nAn example was using a spray bottle to wet the paper and then when using crayon the effect is a tie-dye look.\nUpcoming\nFriday, November 14th Farm Day School Wide Event\nFriends of SOPL Jewelry Sale\nSat. 11/15 and Sun 11/16 at the Baird Center\nWeek of November 17th - Expressions of Thanks for Teachers - cards, pictures appreciated\nThursday, November 20th - PEP Sponsored Teacher Lunch\nTuesday, November 25th \r\n- PEP Pizza Cupcake Lunch\nWednesday, November 26th - noon dismissal - no lunch served\nThursday and Friday, November 27th and 28th SOCDS closed for Thanksgiving Holiday\nDecember 31st - Flu Immunization Proof shared with SOCDS\nClass Directory\nSchool Calendar\nSimplyGourmet Lunch Link\n@SOCDSMOMENTS\nLogistics\nDress Appropriately for the Weather:\nPlease dress your child in appropriate gear for the day.  There is no bad weather just poor clothing.\nMorning Snack\n:  Please send in a morning, and if your child is staying for enrichment please send in an afternoon snack as well.  We generally allow children to choose their food and to listen to their bodies, but if you have any particular preference for what they eat and when, please just label the containers and we will accommodate.  Please remember we are a NUT FREE environment.\nWater Bottles\n:  Please send in a labeled water bottle with your child each day.  We do make sure that they drink water \r\nthroughout the day.  We have two water fountains which we use to refill the bottles (so they may come home full.)\nParking:\nPlease remember that Vose Avenue is an active busy street.  Please pull up on the\nschool side\nof Vose in front of the school.  It is safest to go around the block instead of turning around in driveways.  For your child's safety please try to have them leave your car from the sidewalk side of the car.\nPlease do not block our neighbors driveway, even for a few minutes.\nTuition:\nAs I receive payments I update the statement and send you a copy.  If you do not receive those from me please let me know.\nHours\nMorning Care 7:30-8:30am\nMorning Drop off is between 8:30-9am\nAfternoon Pick Up is between 3:10- 3:20pm\nExtended Day 3:20-5:30/5:45pm\nSouth Orange Country Day School\n461 Vose Avenue, South Orange\n973.762.6451\nYou are receiving this email because your child attends SOCDS.  If you no longer wish to receive these updates, please unsubscribe below.\nUnsubscribe",
  "links": [
    {
      "label": "Email Ms. Annemarie",
      "url": "https://email.4elbows.com/t/y-l-qutqz-hdtdkklre-y/"
    },
    {
      "label": "online catelog is here",
      "url": "https://email.4elbows.com/t/y-l-qutqz-hdtdkklre-j/"
    },
    {
      "label": ".",
      "url": "https://email.4elbows.com/t/y-l-qutqz-hdtdkklre-t/"
    },
    {
      "label": "Friends of SOPL Jewelry Sale",
      "url": "https://email.4elbows.com/t/y-l-qutqz-hdtdkklre-i/"
    },
    {
      "label": "Class Directory",
      "url": "https://email.4elbows.com/t/y-l-qutqz-hdtdkklre-d/"
    },
    {
      "label": "School Calendar",
      "url": "https://email.4elbows.com/t/y-l-qutqz-hdtdkklre-h/"
    },
    {
      "label": "SimplyGourmet Lunch Link",
      "url": "https://email.4elbows.com/t/y-l-qutqz-hdtdkklre-k/"
    },
    {
      "label": "@SOCDSMOMENTS",
      "url": "https://email.4elbows.com/t/y-l-qutqz-hdtdkklre-u/"
    },
    {
      "label": "Unsubscribe",
      "url": "https://email.4elbows.com/t/y-u-qutqz-hdtdkklre-b/"
    }
  ]
}